CHIPy8-0.1.2.data/scripts/chipy8
chipy8/Chip8.py
chipy8/Interface.py
chipy8/__init__.py
chipy8/beep.mp3
chipy8/config.py
chipy8/font.ch8
chipy8/icon.png
chipy8/run.py
CHIPy8-0.1.2.dist-info/LICENSE
CHIPy8-0.1.2.dist-info/METADATA
CHIPy8-0.1.2.dist-info/WHEEL
CHIPy8-0.1.2.dist-info/top_level.txt
CHIPy8-0.1.2.dist-info/RECORD
