Metadata-Version: 2.1
Name: CHIPy8
Version: 0.1.2
Summary: CHIP8 interpreter
Home-page: https://github.com/jtl125/CHIPy8
Author: Jaime Travesedo
Author-email: jaimetravesedo125@gmail.com
License: UNKNOWN
Project-URL: Bug Tracker, https://github.com/jtl125/CHIPy8/issues
Platform: UNKNOWN
Classifier: Programming Language :: Python :: 3
Classifier: License :: OSI Approved :: MIT License
Classifier: Operating System :: OS Independent
Requires-Python: >=3.8
License-File: LICENSE
Requires-Dist: pygame
